rinex_parser/__init__.py
rinex_parser/cli.py
rinex_parser/constants.py
rinex_parser/logger.py
rinex_parser/obs_epoch.py
rinex_parser/obs_factory.py
rinex_parser/obs_header.py
rinex_parser/obs_parser.py
rinex_parser/obs_quality.py
rinex_parser/obs_reader.py
rinex_parser/timescale.py
rinex_parser/utils.py
rinex_parser/scripts/__init__.py
rinex_parser/scripts/main.py
rinexparser-1.2.2.dist-info/METADATA
rinexparser-1.2.2.dist-info/WHEEL
rinexparser-1.2.2.dist-info/entry_points.txt
rinexparser-1.2.2.dist-info/licenses/LICENSE.txt
rinexparser-1.2.2.dist-info/RECORD
