Metadata-Version: 2.4
Name: RinexParser
Version: 1.2.2
Summary: A tool to parse, check and resample Rinex files
Project-URL: Homepage, https://github.com/a5bru/RinexParser
Project-URL: Issues, https://github.com/a5bru/RinexParser/issues
Author-email: Juergen Fredriksson <surveyor@quantentunnel.de>
License-Expression: GPL-3.0-or-later
License-File: LICENSE.txt
Requires-Python: >=3.8
